Pipeline/Parts/Old/Register/regfile.v

module regfile (
    // This component stores state, so needs a clock and a reset
    clock,
    reset,

    // The register file has two ports: one read, one write

    // Inputs
    rd1,        // Which register to read for read port 1

    wr1,        // Which register to write for write port 1 (WP1)
    wr1_data,   // What to write to the register for WP1
    wr1_enable, // Whether or not we should write to WP1 this cycle

    // Outputs
    rd1_data    // The data stored in the register specified by rd1
    );

input clock;
input reset;

input [1:0]     rd1;            // 2 bits wide, because we have 4 registers
input [1:0]     wr1;
input [15:0]    wr1_data;       // 16 bits wide, because that is our data width
input           wr1_enable;

output [15:0]  rd1_data;        // 16 bits wide, because that is our data width

//// Internal variables
reg [15:0] registers [0:3];

// This is the sequential bit of the register file. We also use the positive
// edge of the reset signal in the sensitivity list to infer an asynchronous
// reset - we want to reset whenever we see that signal, rather than just on a
// clock edge.
always @(posedge clock or posedge reset) begin
    if (reset) begin
        // reset the registers
        registers[0] = 0;
        registers[1] = 0;
        registers[2] = 0;
        registers[3] = 0;
    end
    else begin
        // This is our sequential part, i.e. we want to copy the data on the
        // write port into the respective register, if write is enabled.
        registers[wr1] = wr1_data;
    end
end

// This is the combinatorial bit of the design - whenever the registers
// change, or the register we want to read changes, we change the output.
assign rd1_data = registers[rd1];

endmodule

Pipeline/Parts/Register/regfile_tb.v
`include "regfile.v"

module regfile_tb;

reg clock;
reg reset;

reg [1:0]     rd1;            // 2 bits wide, because we have 4 registers
reg [1:0]     wr1;
reg [15:0]    wr1_data;       // 16 bits wide, because that is our data width
reg           wr1_enable;

wire [15:0]  rd1_data;        // 16 bits wide, because that is our data width

// Declare the component, and hook it up to our regs/wires
regfile regfile_impl(
    clock,
    reset,
    rd1,
    wr1,
    wr1_data,
    wr1_enable,
    rd1_data);

initial begin
    clock = 0;
    reset = 0;
    rd1 = 0;
    wr1 = 0;
    wr1_data = 0;
    wr1_enable = 0;
    $dumpvars;

    // Initially reset
#5  reset = 1;
#20 reset = 0;
#20

    // Start some tests //////////////////////////////////////////////////////

    // Write 0x10 to register 0
    wr1_data    = 16'h0010;
    wr1         = 0;
    wr1_enable  = 1;
#20
    // Write 0x20 to register 1
    wr1_data    = 16'h0020;
    wr1         = 1;
    wr1_enable  = 1;
#20
    // Write 0x20 to register 2
    wr1_data    = 16'hABCD;
    wr1         = 2;
    wr1_enable  = 1;
#20
    wr1_enable  = 0;

    // Read out register 1
    rd1         = 1;
#20
    // Read out register 2
    rd1         = 2;

    #10 $finish;
end


always
    #10 clock = ~clock;

endmodule

Pipeline/Parts/Old/Register/dump.vcd
$date
	Tue Jul 14 15:19:11 2015
$end
$version
	Icarus Verilog
$end
$timescale
	1s
$end
$scope module regfile_tb $end
$var wire 16 ! rd1_data [15:0] $end
$var reg 1 " clock $end
$var reg 2 # rd1 [1:0] $end
$var reg 1 $ reset $end
$var reg 2 % wr1 [1:0] $end
$var reg 16 & wr1_data [15:0] $end
$var reg 1 ' wr1_enable $end
$scope module regfile_impl $end
$var wire 1 ( clock $end
$var wire 2 ) rd1 [1:0] $end
$var wire 16 * rd1_data [15:0] $end
$var wire 1 + reset $end
$var wire 2 , wr1 [1:0] $end
$var wire 16 - wr1_data [15:0] $end
$var wire 1 . wr1_enable $end
$upscope $end
$upscope $end
$enddefinitions $end
#0
$dumpvars
0.
b0 -
b0 ,
0+
bx *
b0 )
0(
0'
b0 &
b0 %
0$
b0 #
0"
bx !
$end
#5
b0 !
b0 *
1$
1+
#10
1"
1(
#20
0"
0(
#25
0$
0+
#30
1"
1(
#40
0"
0(
#45
1'
1.
b10000 &
b10000 -
#50
b10000 !
b10000 *
1"
1(
#60
0"
0(
#65
b1 %
b1 ,
b100000 &
b100000 -
#70
1"
1(
#80
0"
0(
#85
b10 %
b10 ,
b1010101111001101 &
b1010101111001101 -
#90
1"
1(
#100
0"
0(
#105
b1 #
b1 )
b100000 !
b100000 *
0'
0.
#110
1"
1(
#120
0"
0(
#125
b10 #
b10 )
b1010101111001101 !
b1010101111001101 *
